{
	"MechaTrail":{
		"engineColor":[100,165,255,120],
		"contrailParticleSizeMult":10.90,
		"contrailParticleDuration":0.12,
		"contrailParticleFinalSizeMult":3.12,		
		"contrailMaxSpeedMult":0.33,
		"contrailAngularVelocityMult":0.33,
		"contrailColor":[33,103,120,52],
		"engineGlowGlowMult":1.45,
		"type":"GLOW" # GLOW or SMOKE
	},
	"MechaTrailZ":{
		"engineColor":[100,165,255,80],
		"contrailParticleSizeMult":5,
		"contrailParticleDuration":0.12,
		"contrailParticleFinalSizeMult":3.12,		
		"contrailMaxSpeedMult":0.33,
		"contrailAngularVelocityMult":0.33,
		"contrailColor":[33,103,120,22],
		"engineGlowGlowMult":1.2,
		"type":"GLOW" # GLOW or SMOKE
	},
	
		
}	
